pytography/__init__.py
pytography/password/__init__.py
pytography/password/algorithms.py
pytography/password/library.py
pytography/token/__init__.py
pytography/token/library.py
pytography/token/segments.py
pytography-0.1.3.dist-info/LICENSE
pytography-0.1.3.dist-info/METADATA
pytography-0.1.3.dist-info/WHEEL
pytography-0.1.3.dist-info/top_level.txt
pytography-0.1.3.dist-info/RECORD
